MANIFEST.in
README.md
setup.py
ahdp/__init__.py
ahdp.egg-info/PKG-INFO
ahdp.egg-info/SOURCES.txt
ahdp.egg-info/dependency_links.txt
ahdp.egg-info/requires.txt
ahdp.egg-info/top_level.txt
ahdp/module_utils/__init__.py
ahdp/module_utils/hdfsbase.py
ahdp/module_utils/hs2base.py
ahdp/modules/__init__.py
ahdp/modules/hadoop/__init__.py
ahdp/modules/hadoop/hdfs/__init__.py
ahdp/modules/hadoop/hdfs/hdfs_snapshot.py
ahdp/modules/hadoop/hdfs/hdfsacl.py
ahdp/modules/hadoop/hdfs/hdfscopy.py
ahdp/modules/hadoop/hdfs/hdfsdownload.py
ahdp/modules/hadoop/hdfs/hdfsfile.py
ahdp/modules/hadoop/hdfs/hdfsfind.py
ahdp/modules/hadoop/hdfs/hdfsstat.py
ahdp/modules/hadoop/hdfs/hdfstoken.py
ahdp/modules/hadoop/hdfs/hdfsupload.py
ahdp/modules/hadoop/hdfs/hdfsxattr.py
ahdp/modules/hadoop/hive/__init__.py
ahdp/modules/hadoop/hive/hive_db.py
ahdp/modules/hadoop/hive/hive_privs.py
examples/simple_playbook.yml
examples/group_vars/lab/lab-encypted.yml
examples/group_vars/lab/lab.yml
examples/group_vars/prod/prod-encypted.yml
examples/group_vars/prod/prod.yml
examples/inventory/ahdp
examples/inventory/cloudera.py
examples/roles/simple_task/defaults/main.yml
examples/roles/simple_task/tasks/main.yml
examples/roles/simple_task/vars/main.yml
tools/cloudera.py
webdocs/check_docs.py
webdocs/create-ansible-webdoc.yml
webdocs/library/ansible_docstring
webdocs/templates/ansible-docs.j2
webdocs/web/hdfs-modules-docs.md
webdocs/web/hive-modules-docs.md