Metadata-Version: 1.1
Name: ahdp
Version: 1.0.0
Summary: pydistcp: python WebHDFS inter/intra-cluster data copy tool.
Home-page: https://github.com/yassineazzouz/ahdp
Author: Yassine Azzouz
Author-email: yassine.azzouz@agmail.com
License: MIT
Platform: UNKNOWN
Classifier: Development Status :: 5 - Production/Stable
Classifier: Intended Audience :: Developers
Classifier: Intended Audience :: System Administrators
Classifier: License :: OSI Approved :: MIT License
Classifier: Programming Language :: Python
Classifier: Programming Language :: Python :: 2.6
Classifier: Programming Language :: Python :: 2.7
Classifier: Programming Language :: Python :: 3.3
Classifier: Programming Language :: Python :: 3.4
